mlib/__init__.py
mlib/config.py
mlib/mongo.py
mlib/mysql.py
mlib/utils/__init__.py
mlib/utils/langconv.py
mlib/utils/zh_wiki.py
bill_mlib-0.5.2.dist-info/LICENSE.txt
bill_mlib-0.5.2.dist-info/METADATA
bill_mlib-0.5.2.dist-info/WHEEL
bill_mlib-0.5.2.dist-info/entry_points.txt
bill_mlib-0.5.2.dist-info/top_level.txt
bill_mlib-0.5.2.dist-info/RECORD
